comports/__init__.py
comports/gui.py
comports/usb_ids.py
comports-0.1.1.dist-info/METADATA
comports-0.1.1.dist-info/WHEEL
comports-0.1.1.dist-info/entry_points.txt
comports-0.1.1.dist-info/licenses/LICENSE
comports-0.1.1.dist-info/RECORD
