Metadata-Version: 2.3
Name: comports
Version: 0.1.1
Summary: A small GUI for launching PuTTY for COM ports
Project-URL: Source, https://github.com/zeevro/comports
Author-email: Zeev Rotshtein <zeevro@gmail.com>
License: This is free and unencumbered software released into the public domain.
License-File: LICENSE
Keywords: COM,GUI,PuTTY,serial
Classifier: Development Status :: 4 - Beta
Classifier: License :: OSI Approved :: The Unlicense (Unlicense)
Classifier: Programming Language :: Python
Classifier: Programming Language :: Python :: 3
Classifier: Programming Language :: Python :: 3 :: Only
Requires-Python: >=3
Requires-Dist: pyserial
